tdrpa/7z.dll
tdrpa/7z.exe
tdrpa/tdworker.cp39-win_amd64.pyd
tdrpa/_tdxlwings/__init__.py
tdrpa/_tdxlwings/_win32patch.py
tdrpa/_tdxlwings/_xlmac.py
tdrpa/_tdxlwings/_xlwindows.py
tdrpa/_tdxlwings/apps.py
tdrpa/_tdxlwings/base_classes.py
tdrpa/_tdxlwings/cli.py
tdrpa/_tdxlwings/com_server.py
tdrpa/_tdxlwings/constants.py
tdrpa/_tdxlwings/expansion.py
tdrpa/_tdxlwings/mac_dict.py
tdrpa/_tdxlwings/main.py
tdrpa/_tdxlwings/quickstart.xlsm
tdrpa/_tdxlwings/quickstart_addin.xlam
tdrpa/_tdxlwings/quickstart_addin_ribbon.xlam
tdrpa/_tdxlwings/quickstart_standalone.xlsm
tdrpa/_tdxlwings/reports.py
tdrpa/_tdxlwings/server.py
tdrpa/_tdxlwings/udfs.py
tdrpa/_tdxlwings/utils.py
tdrpa/_tdxlwings/xlwings-0.31.6.applescript
tdrpa/_tdxlwings/xlwings.bas
tdrpa/_tdxlwings/xlwings_custom_addin.bas
tdrpa/_tdxlwings/xlwingslib.cp38-win_amd64.pyd
tdrpa/_tdxlwings/__pycache__/__init__.cpython-311.pyc
tdrpa/_tdxlwings/__pycache__/__init__.cpython-38.pyc
tdrpa/_tdxlwings/__pycache__/_win32patch.cpython-311.pyc
tdrpa/_tdxlwings/__pycache__/_win32patch.cpython-38.pyc
tdrpa/_tdxlwings/__pycache__/_xlwindows.cpython-311.pyc
tdrpa/_tdxlwings/__pycache__/_xlwindows.cpython-38.pyc
tdrpa/_tdxlwings/__pycache__/apps.cpython-311.pyc
tdrpa/_tdxlwings/__pycache__/apps.cpython-38.pyc
tdrpa/_tdxlwings/__pycache__/base_classes.cpython-311.pyc
tdrpa/_tdxlwings/__pycache__/base_classes.cpython-38.pyc
tdrpa/_tdxlwings/__pycache__/com_server.cpython-311.pyc
tdrpa/_tdxlwings/__pycache__/com_server.cpython-38.pyc
tdrpa/_tdxlwings/__pycache__/constants.cpython-311.pyc
tdrpa/_tdxlwings/__pycache__/constants.cpython-38.pyc
tdrpa/_tdxlwings/__pycache__/expansion.cpython-311.pyc
tdrpa/_tdxlwings/__pycache__/expansion.cpython-38.pyc
tdrpa/_tdxlwings/__pycache__/main.cpython-311.pyc
tdrpa/_tdxlwings/__pycache__/main.cpython-38.pyc
tdrpa/_tdxlwings/__pycache__/udfs.cpython-311.pyc
tdrpa/_tdxlwings/__pycache__/udfs.cpython-38.pyc
tdrpa/_tdxlwings/__pycache__/utils.cpython-311.pyc
tdrpa_tdworker-1.2.19.32.dist-info/METADATA
tdrpa_tdworker-1.2.19.32.dist-info/WHEEL
tdrpa_tdworker-1.2.19.32.dist-info/top_level.txt
tdrpa_tdworker-1.2.19.32.dist-info/RECORD
