Metadata-Version: 2.1
Name: tdrpa.tdworker
Version: 1.2.19.32
Summary: tdworker for tdrpa developers. supports python3.8+, windows x64
Home-page: https://gitee.com/tdworker/command/wikis
Author: vx:RPA_CREATOR
Author-email: virtualpartner@qq.com
License: Apache 2.0
Keywords: rpa,RPA,tdRPA,tdworker,rpaworker,worker,uiautomation,uia,creator,windows,python,bot,robot,aigc,ai,xpath,按键精灵,办公自动化,影刀,UIBOT,实在智能,uipath
Platform: Windows Only
Classifier: Programming Language :: Python :: 3
Classifier: Operating System :: Microsoft :: Windows
Requires-Dist: tdrpa.tdcore>=1.2.22
Requires-Dist: pywin32
Requires-Dist: pyperclip
Requires-Dist: WMI
Requires-Dist: pycryptodome
Requires-Dist: cryptography
Requires-Dist: psutil
Requires-Dist: mss
Requires-Dist: opencv-python
Requires-Dist: numpy
Requires-Dist: pyzmq
Requires-Dist: pillow
Requires-Dist: requests
Requires-Dist: configobj
Requires-Dist: charset-normalizer
